odoo/addons/pos_order_return/README.rst
odoo/addons/pos_order_return/__init__.py
odoo/addons/pos_order_return/__manifest__.py
odoo/addons/pos_order_return/demo/product_product.xml
odoo/addons/pos_order_return/i18n/ca.po
odoo/addons/pos_order_return/i18n/es.po
odoo/addons/pos_order_return/i18n/fr.po
odoo/addons/pos_order_return/i18n/it.po
odoo/addons/pos_order_return/i18n/pos_order_return.pot
odoo/addons/pos_order_return/models/__init__.py
odoo/addons/pos_order_return/models/pos_order.py
odoo/addons/pos_order_return/models/product_template.py
odoo/addons/pos_order_return/readme/CONFIGURE.rst
odoo/addons/pos_order_return/readme/CONTRIBUTORS.rst
odoo/addons/pos_order_return/readme/CREDITS.rst
odoo/addons/pos_order_return/readme/DESCRIPTION.rst
odoo/addons/pos_order_return/readme/ROADMAP.rst
odoo/addons/pos_order_return/readme/USAGE.rst
odoo/addons/pos_order_return/static/description/icon.png
odoo/addons/pos_order_return/static/description/index.html
odoo/addons/pos_order_return/static/description/initial_pos_order_required.png
odoo/addons/pos_order_return/static/description/partial_return_wizard.png
odoo/addons/pos_order_return/static/description/product_returnable_bottle.png
odoo/addons/pos_order_return/static/description/returned_qty_over_initial.png
odoo/addons/pos_order_return/static/description/sum_returned_qty_over_initial.png
odoo/addons/pos_order_return/static/img/product_returnable_bottle-image.jpg
odoo/addons/pos_order_return/tests/__init__.py
odoo/addons/pos_order_return/tests/test_pos_order_return.py
odoo/addons/pos_order_return/views/pos_order_view.xml
odoo/addons/pos_order_return/views/product_product_view.xml
odoo/addons/pos_order_return/wizard/__init__.py
odoo/addons/pos_order_return/wizard/pos_partial_return_wizard.py
odoo/addons/pos_order_return/wizard/pos_partial_return_wizard_view.xml
odoo12_addon_pos_order_return-12.0.1.1.0.dist-info/METADATA
odoo12_addon_pos_order_return-12.0.1.1.0.dist-info/WHEEL
odoo12_addon_pos_order_return-12.0.1.1.0.dist-info/top_level.txt
odoo12_addon_pos_order_return-12.0.1.1.0.dist-info/RECORD
